devtools_diff/__init__.py
devtools_diff-1.0.1.dist-info/METADATA
devtools_diff-1.0.1.dist-info/WHEEL
devtools_diff-1.0.1.dist-info/top_level.txt
devtools_diff-1.0.1.dist-info/RECORD
