Metadata-Version: 2.1
Name: devtools-diff
Version: 1.0.1
Summary: Text diff checker
Home-page: https://devtools.at/tools/diff-checker
Author: DevTools.at
Author-email: hello@devtools.at
Project-URL: Homepage, https://devtools.at/tools/diff-checker
Project-URL: Repository, https://github.com/devtools-at/diff-checker
Classifier: Development Status :: 4 - Beta
Classifier: Intended Audience :: Developers
Classifier: License :: OSI Approved :: MIT License
Classifier: Programming Language :: Python :: 3
Requires-Python: >=3.8
